<?xml version="1.0" encoding="UTF-8" ?>
<Module>
  <ModulePrefs title="LambdaJ Google Gadget" />
  <Content type="html">
     <![CDATA[
        <div style="width:425px" id="__ss_6688488"><strong style="display:block;margin:12px 0 4px">
        <a href="http://www.slideshare.net/mariofusco/no-more-loops-with-lambdaj" title="No more loops with lambdaj">No more loops with lambdaj</a></strong>
        <object id="__sse6688488" width="425" height="355">
        <param name="movie" value="http://static.slidesharecdn.com/swf/ssplayer2.swf?doc=lambdaj-110124161033-phpapp01&stripped_title=no-more-loops-with-lambdaj&userName=mariofusco" />
        <param name="allowFullScreen" value="true"/><param name="allowScriptAccess" value="always"/>
        <embed name="__sse6688488" src="http://static.slidesharecdn.com/swf/ssplayer2.swf?doc=lambdaj-110124161033-phpapp01&stripped_title=no-more-loops-with-lambdaj&userName=mariofusco" type="application/x-shockwave-flash" allowscriptaccess="always" allowfullscreen="true" width="425" height="355"></embed>
        </object>
        <div style="padding:5px 0 12px">View more <a href="http://www.slideshare.net/">presentations</a> from <a href="http://www.slideshare.net/mariofusco">Mario Fusco</a>.
        </div>
        </div>
     ]]>
  </Content>
</Module>
